RNG.cpython-38-darwin.so
RNG-1.9.1.dist-info/LICENSE
RNG-1.9.1.dist-info/METADATA
RNG-1.9.1.dist-info/WHEEL
RNG-1.9.1.dist-info/top_level.txt
RNG-1.9.1.dist-info/RECORD
