Metadata-Version: 2.1
Name: RNG
Version: 1.9.1
Summary: Python3 API for the C++ Random Library
Home-page: UNKNOWN
Author: Robert Sharp
Author-email: webmaster@sharpdesigndigital.com
License: Free for non-commercial use
Keywords: rng,Mersenne Twister,random number generator,cpp random library,random integer,Bernoulli,binomial,negative binomial,geometric,poisson,discrete,normal,distribution,log normal,gamma,exponential,weibull,extreme value,chi squared,cauchy,fisher f,student t
Platform: Darwin
Platform: Linux
Classifier: Development Status :: 7 - Inactive
Classifier: Programming Language :: Python :: 3.7
Classifier: Programming Language :: Cython
Classifier: Programming Language :: C++
Classifier: Operating System :: MacOS :: MacOS X
Classifier: Operating System :: POSIX :: Linux
Classifier: Topic :: Software Development :: Libraries :: Python Modules
Requires: Cython
Requires-Python: >=3.6
